{"cameraMode":{"drawMode":0,"name":"Shaded","section":"Shading Mode"},"sceneLighting":true,"audioPlay":false,"sceneViewState":{"showFog":true,"showMaterialUpdate":false,"showSkybox":true,"showFlares":true,"showImageEffects":true,"showParticleSystems":true},"in2DMode":false,"pivot":{"x":433.55340576171877,"y":557.8982543945313,"z":341.30401611328127},"rotation":{"x":0.13155360519886018,"y":0.6556774973869324,"z":-0.11749201267957688,"w":0.734151303768158},"size":1529.4925537109375,"orthographic":false}